{"is_source_file": true, "format": "Dart", "description": "This file defines a mock catalog for audiobooks, providing a static method that returns a list of Audiobook objects with hardcoded sample data. It is intended for use as a placeholder or dummy data source in a frontend or testing environment.", "external_files": ["../models/audiobook.dart"], "external_methods": [], "published": ["MockCatalog"], "classes": [{"name": "MockCatalog", "description": "A class providing a static method to retrieve a list of mock Audiobook items."}], "methods": [{"name": "items", "description": "Returns a list of sample Audiobook objects representing a mock catalog."}], "calls": ["Audiobook"], "search-terms": ["MockCatalog", "mock_catalog.dart", "Audiobook", "sample data", "mock data", "catalog"], "state": 2, "file_id": 23, "knowledge_revision": 57, "git_revision": "", "hash": "659dab997664a37b8eee7b0313ad8216", "format-version": 4, "code-base-name": "audiobook_store_frontend", "filename": "audiobook_store_frontend/lib/src/data/mock_catalog.dart", "revision_history": [{"57": ""}]}